hellocdw.py
hellocdw-0.0.2.dist-info/METADATA
hellocdw-0.0.2.dist-info/WHEEL
hellocdw-0.0.2.dist-info/top_level.txt
hellocdw-0.0.2.dist-info/RECORD
