Metadata-Version: 2.1
Name: hellocdw
Version: 0.0.2
Summary: Some description here!
Home-page: UNKNOWN
License: UNKNOWN
Platform: UNKNOWN
Classifier: Programming Language :: Python :: 3.6
